{
  "alerts": [
    {
      "id": "f2cb5536en",
      "first_name": "Jaime",
      "last_name": "Stokes",
      "email": "Heloise.Farrell71@hotmail.com",
      "address": {
        "street": "Ledner Landing",
        "zip_code": "74264",
        "city": "West Devonte",
        "number": 213,
        "state": "South Carolina"
      }
    },
    {
      "id": "cn9kvov5b2",
      "first_name": "Scarlett",
      "last_name": "Bartell",
      "email": "Gertrude.Baumbach13@hotmail.com",
      "address": {
        "street": "Shemar Pass",
        "zip_code": "51383-7489",
        "city": "New Joaquin",
        "number": 65,
        "state": "California"
      }
    },
    {
      "id": "1jlwk26zqn",
      "first_name": "Miles",
      "last_name": "Stiedemann",
      "email": "Emory93@gmail.com",
      "address": {
        "street": "Anne Green",
        "zip_code": "92493",
        "city": "Port Burdette",
        "number": 840,
        "state": "Virginia"
      }
    },
    {
      "id": "ysrh16zgbef",
      "first_name": "Shyann",
      "last_name": "Hoppe",
      "email": "Reina_Gottlieb@yahoo.com",
      "address": {
        "street": "Hilton Ville",
        "zip_code": "67447-8619",
        "city": "Anitabury",
        "number": 73,
        "state": "Wyoming"
      }
    },
    {
      "id": "7m3505z4ry",
      "first_name": "Fredrick",
      "last_name": "Hodkiewicz",
      "email": "Horacio_Hilll@gmail.com",
      "address": {
        "street": "Carlotta Overpass",
        "zip_code": "97231",
        "city": "South Kingside",
        "number": 64,
        "state": "South Dakota"
      }
    },
    {
      "id": "rqhe3yrmiq",
      "first_name": "Jayson",
      "last_name": "Smitham",
      "email": "Franz39@gmail.com",
      "address": {
        "street": "Hagenes Forge",
        "zip_code": "53767-6654",
        "city": "South Kristin",
        "number": 776,
        "state": "Delaware"
      }
    },
    {
      "id": "mdfq1yvcqz",
      "first_name": "Hayden",
      "last_name": "Stark",
      "email": "Carissa97@hotmail.com",
      "address": {
        "street": "Labadie Circles",
        "zip_code": "24521-5495",
        "city": "Christiansenton",
        "number": 480,
        "state": "Kentucky"
      }
    },
    {
      "id": "uyc1ask67u",
      "first_name": "Quinn",
      "last_name": "Doyle",
      "email": "Jacinto_Abshire@gmail.com",
      "address": {
        "street": "Anderson Court",
        "zip_code": "06255",
        "city": "Michalebury",
        "number": 330,
        "state": "New Mexico"
      }
    },
    {
      "id": "obr2xsj7q6",
      "first_name": "Marilie",
      "last_name": "Bechtelar",
      "email": "Bria_King98@yahoo.com",
      "address": {
        "street": "Mann Road",
        "zip_code": "69799-5215",
        "city": "Devanteland",
        "number": 539,
        "state": "Idaho"
      }
    },
    {
      "id": "1pogznh7n9",
      "first_name": "Jayce",
      "last_name": "Ruecker",
      "email": "Sam.Konopelski@hotmail.com",
      "address": {
        "street": "Okuneva Corner",
        "zip_code": "91694",
        "city": "West Bret",
        "number": 784,
        "state": "Nevada"
      }
    },
    {
      "id": "7nmla5atra",
      "first_name": "Destin",
      "last_name": "Kilback",
      "email": "Lizeth44@yahoo.com",
      "address": {
        "street": "Reece Prairie",
        "zip_code": "44500",
        "city": "Port Tonishire",
        "number": 507,
        "state": "Tennessee"
      }
    },
    {
      "id": "2olnxnwjxg",
      "first_name": "Herminio",
      "last_name": "Balistreri",
      "email": "Hulda36@gmail.com",
      "address": {
        "street": "Wisoky Junction",
        "zip_code": "86268-3347",
        "city": "West Lexusville",
        "number": 458,
        "state": "Nebraska"
      }
    },
    {
      "id": "f7wjhvvbgy",
      "first_name": "Opal",
      "last_name": "Williamson",
      "email": "Kaley55@yahoo.com",
      "address": {
        "street": "Vickie Meadows",
        "zip_code": "16403",
        "city": "Port Torey",
        "number": 431,
        "state": "Alaska"
      }
    },
    {
      "id": "cm0jbdt3rt",
      "first_name": "Marianna",
      "last_name": "Strosin",
      "email": "Rolando_Harris77@hotmail.com",
      "address": {
        "street": "Collins Course",
        "zip_code": "41551-1532",
        "city": "Schaefermouth",
        "number": 570,
        "state": "Indiana"
      }
    },
    {
      "id": "xanbiyxpur",
      "first_name": "Burdette",
      "last_name": "Larkin",
      "email": "Eunice_Lindgren@gmail.com",
      "address": {
        "street": "Claudia Station",
        "zip_code": "48774",
        "city": "South Keith",
        "number": 780,
        "state": "Louisiana"
      }
    },
    {
      "id": "jo1fabg43u",
      "first_name": "Bernardo",
      "last_name": "Dooley",
      "email": "Stella19@yahoo.com",
      "address": {
        "street": "Mandy Shore",
        "zip_code": "22405",
        "city": "Lake Diegoland",
        "number": 241,
        "state": "Maryland"
      }
    },
    {
      "id": "epmcbwycco",
      "first_name": "Fatima",
      "last_name": "Herman",
      "email": "Santina_Goyette18@yahoo.com",
      "address": {
        "street": "Kassulke Estates",
        "zip_code": "91354-6700",
        "city": "Port Brianhaven",
        "number": 16,
        "state": "Texas"
      }
    },
    {
      "id": "jqzrgiehxkj",
      "first_name": "Tyrel",
      "last_name": "Schuster",
      "email": "Delpha36@yahoo.com",
      "address": {
        "street": "Benton Overpass",
        "zip_code": "41720-2978",
        "city": "Lake Jeramie",
        "number": 945,
        "state": "Michigan"
      }
    },
    {
      "id": "x73wmyubhg",
      "first_name": "Rafaela",
      "last_name": "Aufderhar",
      "email": "Clara.Jenkins@hotmail.com",
      "address": {
        "street": "Evalyn Manors",
        "zip_code": "93698-3702",
        "city": "Larsonview",
        "number": 771,
        "state": "Rhode Island"
      }
    },
    {
      "id": "fcwc1hkok2h",
      "first_name": "Jessie",
      "last_name": "Quigley",
      "email": "Lupe.Bradtke58@yahoo.com",
      "address": {
        "street": "Jaskolski Plain",
        "zip_code": "06988-0912",
        "city": "Brionnaberg",
        "number": 357,
        "state": "California"
      }
    },
    {
      "id": "tnuywgjqg5i",
      "first_name": "Jackeline",
      "last_name": "Mertz",
      "email": "Lonny.Gutmann59@gmail.com",
      "address": {
        "street": "Peter Camp",
        "zip_code": "94495-4345",
        "city": "Shaynamouth",
        "number": 344,
        "state": "Hawaii"
      }
    },
    {
      "id": "u2riyyuu1z",
      "first_name": "Ezekiel",
      "last_name": "Goodwin",
      "email": "Cecil_Bins16@gmail.com",
      "address": {
        "street": "Clementina Groves",
        "zip_code": "90975-4568",
        "city": "Hayesside",
        "number": 150,
        "state": "New Mexico"
      }
    },
    {
      "id": "vrbifok9ya",
      "first_name": "Mohammed",
      "last_name": "Hayes",
      "email": "Junius_Kutch23@gmail.com",
      "address": {
        "street": "Hills Roads",
        "zip_code": "55043",
        "city": "Tomasaburgh",
        "number": 572,
        "state": "Delaware"
      }
    },
    {
      "id": "gs5wj2ho06",
      "first_name": "Janessa",
      "last_name": "Jones",
      "email": "Kadin75@yahoo.com",
      "address": {
        "street": "Enrique Views",
        "zip_code": "72737",
        "city": "Bernieport",
        "number": 522,
        "state": "Colorado"
      }
    },
    {
      "id": "7i8frii9yb",
      "first_name": "Roman",
      "last_name": "White",
      "email": "Alexane_Bruen32@yahoo.com",
      "address": {
        "street": "Giovanny Shoals",
        "zip_code": "78666-1775",
        "city": "Lomamouth",
        "number": 242,
        "state": "Florida"
      }
    },
    {
      "id": "jfz6hakibc",
      "first_name": "Pietro",
      "last_name": "Nikolaus",
      "email": "Cordie.Krajcik@yahoo.com",
      "address": {
        "street": "Amani Port",
        "zip_code": "18940-8557",
        "city": "North Alanistown",
        "number": 631,
        "state": "Ohio"
      }
    },
    {
      "id": "55487ajbkv",
      "first_name": "Norwood",
      "last_name": "Romaguera",
      "email": "Ashly60@yahoo.com",
      "address": {
        "street": "Adonis Manors",
        "zip_code": "93601-1286",
        "city": "Gerryside",
        "number": 12,
        "state": "Connecticut"
      }
    },
    {
      "id": "r88pmk5hul",
      "first_name": "Rafael",
      "last_name": "Goldner",
      "email": "Valentin93@yahoo.com",
      "address": {
        "street": "Hollis Extensions",
        "zip_code": "01721",
        "city": "Collierfurt",
        "number": 190,
        "state": "Montana"
      }
    },
    {
      "id": "l9e335xwd5",
      "first_name": "Eloy",
      "last_name": "Simonis",
      "email": "Rene29@yahoo.com",
      "address": {
        "street": "Graham Cliffs",
        "zip_code": "26551-6039",
        "city": "West Aylin",
        "number": 512,
        "state": "New York"
      }
    },
    {
      "id": "e2mh1bt5k5f",
      "first_name": "Derick",
      "last_name": "Spencer",
      "email": "Elmer_Shanahan@gmail.com",
      "address": {
        "street": "Hermiston Pine",
        "zip_code": "13202-7435",
        "city": "Morarstad",
        "number": 482,
        "state": "Idaho"
      }
    },
    {
      "id": "z6no392el7",
      "first_name": "Maritza",
      "last_name": "Effertz",
      "email": "Jamaal_Tromp@gmail.com",
      "address": {
        "street": "Abbigail Station",
        "zip_code": "15791-1419",
        "city": "North Alexandreside",
        "number": 124,
        "state": "Indiana"
      }
    },
    {
      "id": "b67muu8z48j",
      "first_name": "Kendra",
      "last_name": "Kilback",
      "email": "Mariano_Bernier@yahoo.com",
      "address": {
        "street": "Mann Stream",
        "zip_code": "01658-0139",
        "city": "Laurencebury",
        "number": 305,
        "state": "Wyoming"
      }
    },
    {
      "id": "30so2kjoobh",
      "first_name": "Olaf",
      "last_name": "Schaden",
      "email": "Dewitt75@hotmail.com",
      "address": {
        "street": "Lorena Route",
        "zip_code": "60433-9401",
        "city": "South Justynstad",
        "number": 698,
        "state": "Maine"
      }
    },
    {
      "id": "iagdifvzel",
      "first_name": "Bud",
      "last_name": "Waelchi",
      "email": "Roosevelt.Hand@yahoo.com",
      "address": {
        "street": "Madilyn Dam",
        "zip_code": "29443",
        "city": "New Wendy",
        "number": 530,
        "state": "Mississippi"
      }
    },
    {
      "id": "8hhcrxe16g",
      "first_name": "Johan",
      "last_name": "Howell",
      "email": "Glen.Ferry38@hotmail.com",
      "address": {
        "street": "Jewel Bridge",
        "zip_code": "39566-1575",
        "city": "Madelynfort",
        "number": 383,
        "state": "Louisiana"
      }
    },
    {
      "id": "c7c779tij2",
      "first_name": "Evert",
      "last_name": "Cremin",
      "email": "Jace_Cartwright42@gmail.com",
      "address": {
        "street": "Alize Bridge",
        "zip_code": "31136",
        "city": "Amayabury",
        "number": 144,
        "state": "Kentucky"
      }
    },
    {
      "id": "prnnj9pps7",
      "first_name": "Saul",
      "last_name": "Lang",
      "email": "Rodrigo99@gmail.com",
      "address": {
        "street": "Rau Well",
        "zip_code": "73633",
        "city": "South Macyberg",
        "number": 492,
        "state": "Hawaii"
      }
    },
    {
      "id": "ciien1w2jt",
      "first_name": "Destiney",
      "last_name": "Powlowski",
      "email": "Ottilie.Hand@hotmail.com",
      "address": {
        "street": "Bergstrom Crossroad",
        "zip_code": "22130",
        "city": "West Margaretefurt",
        "number": 422,
        "state": "Texas"
      }
    },
    {
      "id": "zko85nyz4b",
      "first_name": "Mylene",
      "last_name": "Gusikowski",
      "email": "Deborah57@yahoo.com",
      "address": {
        "street": "Tiara Village",
        "zip_code": "34565-9842",
        "city": "Port Vernerport",
        "number": 506,
        "state": "Hawaii"
      }
    },
    {
      "id": "zya0dvvmrs",
      "first_name": "Kareem",
      "last_name": "Stehr",
      "email": "Raleigh.Mills4@hotmail.com",
      "address": {
        "street": "Abbott Via",
        "zip_code": "01682",
        "city": "Port Carmelofurt",
        "number": 645,
        "state": "Montana"
      }
    },
    {
      "id": "kj627ye1s4",
      "first_name": "Estell",
      "last_name": "Goldner",
      "email": "Madie.Blanda@yahoo.com",
      "address": {
        "street": "Elian Ferry",
        "zip_code": "48074",
        "city": "West Furman",
        "number": 884,
        "state": "Nebraska"
      }
    },
    {
      "id": "phrc9qbhik",
      "first_name": "Stephon",
      "last_name": "Kutch",
      "email": "Abby3@gmail.com",
      "address": {
        "street": "Guadalupe Corner",
        "zip_code": "63275-6432",
        "city": "Port Freeda",
        "number": 264,
        "state": "Ohio"
      }
    },
    {
      "id": "5mfpvegtyik",
      "first_name": "Jonathan",
      "last_name": "Kovacek",
      "email": "Jamel51@gmail.com",
      "address": {
        "street": "Pagac Dale",
        "zip_code": "62412",
        "city": "Lake Della",
        "number": 570,
        "state": "Georgia"
      }
    },
    {
      "id": "89sgssppnw",
      "first_name": "Margaret",
      "last_name": "Toy",
      "email": "Jonathon43@hotmail.com",
      "address": {
        "street": "Hahn Roads",
        "zip_code": "51040-5179",
        "city": "O'Haraburgh",
        "number": 34,
        "state": "South Dakota"
      }
    },
    {
      "id": "ami97qg9re",
      "first_name": "Mikel",
      "last_name": "Schmeler",
      "email": "Krystina.Jacobs83@hotmail.com",
      "address": {
        "street": "Aliyah Lake",
        "zip_code": "61661-2074",
        "city": "North Suzanne",
        "number": 951,
        "state": "Maine"
      }
    },
    {
      "id": "z94okpkbssf",
      "first_name": "Clifford",
      "last_name": "Wuckert",
      "email": "Raheem42@hotmail.com",
      "address": {
        "street": "Meda Turnpike",
        "zip_code": "27047",
        "city": "Leannonfurt",
        "number": 947,
        "state": "Iowa"
      }
    },
    {
      "id": "3rjt5gyptf",
      "first_name": "Sandy",
      "last_name": "Koepp",
      "email": "Chauncey.Daniel@gmail.com",
      "address": {
        "street": "Kulas Square",
        "zip_code": "11193-1076",
        "city": "Port Daishamouth",
        "number": 375,
        "state": "Montana"
      }
    },
    {
      "id": "apkxf6u0e3i",
      "first_name": "Ottilie",
      "last_name": "Bashirian",
      "email": "Danika_Hyatt@hotmail.com",
      "address": {
        "street": "Ofelia Mills",
        "zip_code": "74619",
        "city": "Lake Beverly",
        "number": 943,
        "state": "Oregon"
      }
    },
    {
      "id": "eyw8vxwsc",
      "first_name": "Bernita",
      "last_name": "Quitzon",
      "email": "Franz.Smitham91@gmail.com",
      "address": {
        "street": "Florence Gateway",
        "zip_code": "60640-4101",
        "city": "Corkeryland",
        "number": 963,
        "state": "South Carolina"
      }
    },
    {
      "id": "0ctlv7fq2z",
      "first_name": "Laurianne",
      "last_name": "Graham",
      "email": "Magdalena.Waters15@hotmail.com",
      "address": {
        "street": "Rae Club",
        "zip_code": "55983",
        "city": "West Friedrichbury",
        "number": 463,
        "state": "New York"
      }
    },
    {
      "id": "9jd2jlnb2c",
      "first_name": "Emanuel",
      "last_name": "Weissnat",
      "email": "Kattie_Breitenberg@hotmail.com",
      "address": {
        "street": "Elton Inlet",
        "zip_code": "66135-1211",
        "city": "Linabury",
        "number": 37,
        "state": "South Carolina"
      }
    },
    {
      "id": "r017r4cpve",
      "first_name": "Kyra",
      "last_name": "Smith",
      "email": "Sadie50@yahoo.com",
      "address": {
        "street": "Filomena Plains",
        "zip_code": "48082-4799",
        "city": "New Mikestad",
        "number": 143,
        "state": "Massachusetts"
      }
    },
    {
      "id": "v9rx83x6a5",
      "first_name": "Wyman",
      "last_name": "Dickinson",
      "email": "Dolores55@yahoo.com",
      "address": {
        "street": "Steuber Key",
        "zip_code": "76069",
        "city": "New David",
        "number": 250,
        "state": "Colorado"
      }
    },
    {
      "id": "hjythixodp",
      "first_name": "Ryleigh",
      "last_name": "Mante",
      "email": "Fleta55@hotmail.com",
      "address": {
        "street": "Unique Pines",
        "zip_code": "57578-2513",
        "city": "Yoshikoborough",
        "number": 41,
        "state": "New York"
      }
    },
    {
      "id": "zhmdub21sb",
      "first_name": "Dayana",
      "last_name": "Renner",
      "email": "Helmer26@hotmail.com",
      "address": {
        "street": "Madyson Field",
        "zip_code": "79654-7374",
        "city": "South Darronville",
        "number": 737,
        "state": "Florida"
      }
    },
    {
      "id": "06v1a4n1rff",
      "first_name": "Terence",
      "last_name": "Hirthe",
      "email": "Kirstin_Parker95@gmail.com",
      "address": {
        "street": "Justyn Circles",
        "zip_code": "79666-3375",
        "city": "Kaylinburgh",
        "number": 331,
        "state": "Illinois"
      }
    },
    {
      "id": "d7dqhmuvec",
      "first_name": "Ray",
      "last_name": "Durgan",
      "email": "Katrina8@hotmail.com",
      "address": {
        "street": "Kuphal Mills",
        "zip_code": "43819",
        "city": "West Tevin",
        "number": 466,
        "state": "Arkansas"
      }
    },
    {
      "id": "zuwvj62xeki",
      "first_name": "Brendon",
      "last_name": "Rodriguez",
      "email": "London87@gmail.com",
      "address": {
        "street": "Israel Radial",
        "zip_code": "70830-2199",
        "city": "North Franz",
        "number": 36,
        "state": "Montana"
      }
    },
    {
      "id": "8ypqh75o3m",
      "first_name": "Leanne",
      "last_name": "Raynor",
      "email": "Minnie.Sauer64@hotmail.com",
      "address": {
        "street": "Kutch Parks",
        "zip_code": "10423",
        "city": "Adolfstad",
        "number": 23,
        "state": "Iowa"
      }
    },
    {
      "id": "s9n3phgovtj",
      "first_name": "Filiberto",
      "last_name": "Armstrong",
      "email": "Taya_DuBuque@hotmail.com",
      "address": {
        "street": "Kirlin Centers",
        "zip_code": "32693",
        "city": "O'Konland",
        "number": 497,
        "state": "Massachusetts"
      }
    },
    {
      "id": "4cbu8rdtkwi",
      "first_name": "Luisa",
      "last_name": "Abshire",
      "email": "Arvid4@gmail.com",
      "address": {
        "street": "Hintz Forks",
        "zip_code": "40706",
        "city": "East Dinaville",
        "number": 607,
        "state": "Montana"
      }
    },
    {
      "id": "izueebfu0o",
      "first_name": "Katrina",
      "last_name": "Ziemann",
      "email": "Stacey11@gmail.com",
      "address": {
        "street": "Schoen Skyway",
        "zip_code": "66308",
        "city": "East Jaquan",
        "number": 859,
        "state": "New Jersey"
      }
    },
    {
      "id": "bmnt6hkhtg",
      "first_name": "Nestor",
      "last_name": "Leannon",
      "email": "Aliya.Schmidt@gmail.com",
      "address": {
        "street": "Nikolas Radial",
        "zip_code": "68344-6967",
        "city": "Port Queenie",
        "number": 362,
        "state": "Missouri"
      }
    },
    {
      "id": "5lzk35dph6",
      "first_name": "Dashawn",
      "last_name": "Rutherford",
      "email": "Celine_Pollich@hotmail.com",
      "address": {
        "street": "Jeanne Circle",
        "zip_code": "03783",
        "city": "Funkberg",
        "number": 639,
        "state": "Vermont"
      }
    },
    {
      "id": "4v1d0rjkqoj",
      "first_name": "Josiah",
      "last_name": "Witting",
      "email": "Nicolette_McClure@hotmail.com",
      "address": {
        "street": "Hayden Inlet",
        "zip_code": "94359-9864",
        "city": "North Kaleigh",
        "number": 701,
        "state": "Ohio"
      }
    },
    {
      "id": "mije0w8tj6",
      "first_name": "Corbin",
      "last_name": "Wilkinson",
      "email": "Rosemarie_Beier@yahoo.com",
      "address": {
        "street": "O'Conner Branch",
        "zip_code": "83984-7325",
        "city": "Calebtown",
        "number": 16,
        "state": "Wisconsin"
      }
    },
    {
      "id": "8ym7i2dkbn",
      "first_name": "Hilbert",
      "last_name": "Rohan",
      "email": "Bridget.Ritchie@gmail.com",
      "address": {
        "street": "Helene Manors",
        "zip_code": "78814",
        "city": "North Cierraside",
        "number": 654,
        "state": "Virginia"
      }
    },
    {
      "id": "56zw346xnd",
      "first_name": "Brian",
      "last_name": "Boyle",
      "email": "Camille_Prosacco@gmail.com",
      "address": {
        "street": "Elfrieda Dale",
        "zip_code": "83035-5387",
        "city": "Virgietown",
        "number": 314,
        "state": "Michigan"
      }
    },
    {
      "id": "jlkax2nktxi",
      "first_name": "Hardy",
      "last_name": "Goldner",
      "email": "Tyrese_Price87@yahoo.com",
      "address": {
        "street": "Larkin Course",
        "zip_code": "35158-8292",
        "city": "Sanfordfort",
        "number": 473,
        "state": "Maryland"
      }
    },
    {
      "id": "muxodqyiqtf",
      "first_name": "Cassandra",
      "last_name": "Strosin",
      "email": "Noemy_Torp33@yahoo.com",
      "address": {
        "street": "Lesch Flat",
        "zip_code": "23089-3040",
        "city": "Breitenbergville",
        "number": 808,
        "state": "Nebraska"
      }
    },
    {
      "id": "a2z3lrtaoi",
      "first_name": "Mathilde",
      "last_name": "Cole",
      "email": "Timothy_Padberg11@hotmail.com",
      "address": {
        "street": "Veronica Locks",
        "zip_code": "66790",
        "city": "Lake Americomouth",
        "number": 84,
        "state": "Maine"
      }
    },
    {
      "id": "9l8zoa01rh",
      "first_name": "Milford",
      "last_name": "Kerluke",
      "email": "Fannie36@yahoo.com",
      "address": {
        "street": "Ziemann Lakes",
        "zip_code": "30131-3556",
        "city": "Feeneyshire",
        "number": 556,
        "state": "Illinois"
      }
    },
    {
      "id": "a08bvde4so",
      "first_name": "Doyle",
      "last_name": "Medhurst",
      "email": "Garrick88@yahoo.com",
      "address": {
        "street": "Bosco Spurs",
        "zip_code": "46766",
        "city": "Heidifurt",
        "number": 523,
        "state": "Alabama"
      }
    },
    {
      "id": "g8tnla0tsoj",
      "first_name": "Reyna",
      "last_name": "Gerlach",
      "email": "Derick31@gmail.com",
      "address": {
        "street": "Lakin Way",
        "zip_code": "66166",
        "city": "Elizaville",
        "number": 891,
        "state": "Mississippi"
      }
    },
    {
      "id": "83mhlx4fcz",
      "first_name": "Arvid",
      "last_name": "Bogan",
      "email": "Green_Howe@gmail.com",
      "address": {
        "street": "Rohan Ranch",
        "zip_code": "82681-5670",
        "city": "Chesterberg",
        "number": 130,
        "state": "North Dakota"
      }
    },
    {
      "id": "l1xc7zvogi",
      "first_name": "Alexandrine",
      "last_name": "Pouros",
      "email": "Lowell_Herman40@hotmail.com",
      "address": {
        "street": "Wilderman Inlet",
        "zip_code": "27251-0945",
        "city": "North Vidalmouth",
        "number": 163,
        "state": "Georgia"
      }
    },
    {
      "id": "xy800chs98g",
      "first_name": "Marlene",
      "last_name": "Jenkins",
      "email": "Boris36@yahoo.com",
      "address": {
        "street": "Maxwell Center",
        "zip_code": "71259",
        "city": "Nikitafurt",
        "number": 424,
        "state": "Nevada"
      }
    },
    {
      "id": "7dwlf23h2u",
      "first_name": "Maria",
      "last_name": "Huels",
      "email": "Ulices_Gibson82@yahoo.com",
      "address": {
        "street": "Tromp Trafficway",
        "zip_code": "39003",
        "city": "Theodoraland",
        "number": 207,
        "state": "Idaho"
      }
    },
    {
      "id": "xv3bdh1r9rl",
      "first_name": "Gloria",
      "last_name": "Mills",
      "email": "Bruce.OConnell@hotmail.com",
      "address": {
        "street": "Mante Cove",
        "zip_code": "54461-0883",
        "city": "Lake Cole",
        "number": 959,
        "state": "Tennessee"
      }
    },
    {
      "id": "i9sjf1pdw9",
      "first_name": "Dayna",
      "last_name": "Grant",
      "email": "Lupe.Yundt44@gmail.com",
      "address": {
        "street": "Swaniawski Underpass",
        "zip_code": "94598",
        "city": "West Bernadetteberg",
        "number": 689,
        "state": "Nevada"
      }
    },
    {
      "id": "7hzs2ux3zn",
      "first_name": "Ronaldo",
      "last_name": "Gaylord",
      "email": "Rosanna_Fadel@hotmail.com",
      "address": {
        "street": "Mills Field",
        "zip_code": "96906-7400",
        "city": "Port Dee",
        "number": 291,
        "state": "South Carolina"
      }
    },
    {
      "id": "8sys65f2ecf",
      "first_name": "Anabelle",
      "last_name": "Harris",
      "email": "Jordyn.Franecki@hotmail.com",
      "address": {
        "street": "Collier Overpass",
        "zip_code": "99845",
        "city": "Jaydafort",
        "number": 397,
        "state": "Maine"
      }
    },
    {
      "id": "lzz87nyg7u",
      "first_name": "Therese",
      "last_name": "Predovic",
      "email": "Dahlia57@yahoo.com",
      "address": {
        "street": "Jammie Walks",
        "zip_code": "93408",
        "city": "Micahmouth",
        "number": 188,
        "state": "Idaho"
      }
    },
    {
      "id": "1qynzeaxi5",
      "first_name": "Neha",
      "last_name": "Beatty",
      "email": "Rusty_Berge@hotmail.com",
      "address": {
        "street": "Morar Forks",
        "zip_code": "01824",
        "city": "Lourdesborough",
        "number": 254,
        "state": "Ohio"
      }
    },
    {
      "id": "vv6etrg2u9",
      "first_name": "Julie",
      "last_name": "Monahan",
      "email": "Gracie24@yahoo.com",
      "address": {
        "street": "Rice Isle",
        "zip_code": "63769-6775",
        "city": "Port Donald",
        "number": 805,
        "state": "Colorado"
      }
    },
    {
      "id": "2ebd7w8phek",
      "first_name": "Linnie",
      "last_name": "Herzog",
      "email": "Elisabeth.Bruen65@gmail.com",
      "address": {
        "street": "Hilll Unions",
        "zip_code": "78457-7940",
        "city": "West Jamir",
        "number": 189,
        "state": "Washington"
      }
    },
    {
      "id": "53i2nggvw2",
      "first_name": "Antonio",
      "last_name": "Bruen",
      "email": "Flo.Adams@yahoo.com",
      "address": {
        "street": "Marilie Knolls",
        "zip_code": "09477-0116",
        "city": "Lake Jessica",
        "number": 225,
        "state": "Washington"
      }
    },
    {
      "id": "2b7h89jd9r",
      "first_name": "Clyde",
      "last_name": "Cormier",
      "email": "Alfonso_Lubowitz@gmail.com",
      "address": {
        "street": "Josiah Streets",
        "zip_code": "33102-0259",
        "city": "Berrystad",
        "number": 353,
        "state": "Oregon"
      }
    },
    {
      "id": "cet0bl7n96",
      "first_name": "Winston",
      "last_name": "Medhurst",
      "email": "Khalil.Bayer@hotmail.com",
      "address": {
        "street": "Corwin Canyon",
        "zip_code": "59616",
        "city": "Bethanyborough",
        "number": 838,
        "state": "Maine"
      }
    },
    {
      "id": "rvwtpanc8ah",
      "first_name": "Velma",
      "last_name": "Walsh",
      "email": "Loy.Boyer19@gmail.com",
      "address": {
        "street": "Edythe Square",
        "zip_code": "21337-1151",
        "city": "East Brianshire",
        "number": 628,
        "state": "Iowa"
      }
    },
    {
      "id": "z2dx6x68fv",
      "first_name": "Rosie",
      "last_name": "Kuhlman",
      "email": "Jeanne_Hilll91@gmail.com",
      "address": {
        "street": "Miller Loaf",
        "zip_code": "97272-9823",
        "city": "Johnfort",
        "number": 548,
        "state": "Maryland"
      }
    },
    {
      "id": "51sueohbcp",
      "first_name": "Oleta",
      "last_name": "Koss",
      "email": "Elta.Denesik39@gmail.com",
      "address": {
        "street": "Iliana Villages",
        "zip_code": "76365-9136",
        "city": "Lake Raymundo",
        "number": 521,
        "state": "Mississippi"
      }
    },
    {
      "id": "iahiyi9l51",
      "first_name": "Florida",
      "last_name": "Kshlerin",
      "email": "Sylvan_McKenzie58@hotmail.com",
      "address": {
        "street": "Patrick Locks",
        "zip_code": "36191-0389",
        "city": "Declanfurt",
        "number": 963,
        "state": "Arizona"
      }
    },
    {
      "id": "0v6no8wbcw",
      "first_name": "Richie",
      "last_name": "Lueilwitz",
      "email": "Grayson41@hotmail.com",
      "address": {
        "street": "Little Manor",
        "zip_code": "46808-8454",
        "city": "Percivalfort",
        "number": 880,
        "state": "New Mexico"
      }
    },
    {
      "id": "ambz02evo7",
      "first_name": "Luis",
      "last_name": "Dickens",
      "email": "Justus.Wuckert@gmail.com",
      "address": {
        "street": "Antonia Rapids",
        "zip_code": "61326",
        "city": "Karineland",
        "number": 607,
        "state": "Alaska"
      }
    },
    {
      "id": "njw19zevyq",
      "first_name": "Georgianna",
      "last_name": "Sauer",
      "email": "Sammie.Bergstrom1@yahoo.com",
      "address": {
        "street": "MacGyver Village",
        "zip_code": "98016-5460",
        "city": "Shaynechester",
        "number": 529,
        "state": "Texas"
      }
    },
    {
      "id": "klmox5ojbm",
      "first_name": "Ralph",
      "last_name": "Walker",
      "email": "Hudson_Flatley@hotmail.com",
      "address": {
        "street": "Tremblay Island",
        "zip_code": "89906",
        "city": "Kerlukeport",
        "number": 737,
        "state": "California"
      }
    },
    {
      "id": "ogri532asqh",
      "first_name": "Minerva",
      "last_name": "Jacobson",
      "email": "Rogers.Leannon77@hotmail.com",
      "address": {
        "street": "Durward Hollow",
        "zip_code": "09340-6655",
        "city": "West Kathrynton",
        "number": 413,
        "state": "North Carolina"
      }
    },
    {
      "id": "4h4w3vbwvjg",
      "first_name": "Aliza",
      "last_name": "Mitchell",
      "email": "Trisha_Huel37@gmail.com",
      "address": {
        "street": "Predovic Grove",
        "zip_code": "15315-3128",
        "city": "South Jay",
        "number": 165,
        "state": "Vermont"
      }
    },
    {
      "id": "7mipvi37in",
      "first_name": "Alvena",
      "last_name": "West",
      "email": "Destiney.Paucek@gmail.com",
      "address": {
        "street": "Leonora Meadows",
        "zip_code": "20211",
        "city": "Quitzonberg",
        "number": 179,
        "state": "Texas"
      }
    }
  ]
}